{
  "questions": [
    {
      "question": "Rozhodněte, které tvrzení je pravdivé:",
      "category": "Číselné a mocninné řady",
      "answers": [
        {
          "text": "Pokud je řada $\\sum_{n=1}^{\\infty} a_n$ konvergentní pak je i řada $\\sum_{n=1}^{\\infty} |a_n|$ konvergentní.",
          "correct": false
        },
        {
          "text": "Řada $\\sum_{n=1}^{\\infty} |a_n|$ může být divergentní i v případě, že řada $\\sum_{n=1}^{\\infty} a_n$ je konvergentní.",
          "correct": true
        },
        {
          "text": "Pokud je řada $\\sum_{n=1}^{\\infty} |a_n|$ konvergentní pak je i řada $\\sum_{n=1}^{\\infty} a_n$ konvergentní.",
          "correct": true
        },
        {
          "text": "Řada $\\sum_{n=1}^{\\infty} |a_n|$ je konvergentní právě tehdy, když je řada $\\sum_{n=1}^{\\infty} a_n$ konvergentní.",
          "correct": false
        }
      ]
    }
  ]
}